unixsocketcs/__init__.py
unixsocketcs/client.py
unixsocketcs/client_api.py
unixsocketcs/client_cli.py
unixsocketcs/server.py
unixsocketcs/server_api.py
unixsocketcs/server_handler.py
unixsocketcs-0.0.3.dist-info/LICENSE.md
unixsocketcs-0.0.3.dist-info/METADATA
unixsocketcs-0.0.3.dist-info/WHEEL
unixsocketcs-0.0.3.dist-info/top_level.txt
unixsocketcs-0.0.3.dist-info/RECORD
