Metadata-Version: 2.1
Name: unixsocketcs
Version: 0.0.3
Summary: Higher level lib to create unix domain socket server and client
Home-page: https://github.com/hellstein/py-unix-socket-cs
Author: phoenix.lv
Author-email: phoenix.grey0108@gmail.com
License: UNKNOWN
Platform: UNKNOWN
Classifier: Programming Language :: Python :: 3
Classifier: License :: OSI Approved :: MIT License
Classifier: Operating System :: OS Independent
